[
  {"text": "cropped nylon track jacket with reflective tape, indigo", "weight": 1.0},
  {"text": "oversized fleece hoodie with kangaroo pocket, heather charcoal", "weight": 1.0},
  {"text": "high-waist ponte joggers with ankle zips, forest green", "weight": 1.0},
  {"text": "fitted scuba knit bomber jacket with ribbed cuffs, burgundy", "weight": 1.0},
  {"text": "longline terry cloth hoodie with side slits, oatmeal beige", "weight": 1.0},
  {"text": "cropped ripstop windbreaker with mesh lining, electric blue", "weight": 1.0},
  {"text": "relaxed-fit cupro jogger set with contrast piping, sage green", "weight": 1.0},
  {"text": "fitted nylon track jacket with color-block panels, coral and navy", "weight": 1.0},
  {"text": "oversized jersey hoodie with dropped shoulders, dusty rose", "weight": 1.0},
  {"text": "high-waist scuba knit leggings with phone pocket, jet black", "weight": 1.0},
  {"text": "cropped nylon windbreaker with hidden hood, sunshine yellow", "weight": 1.0},
  {"text": "fitted ponte blazer with athleisure stretch, camel tan", "weight": 1.0},
  {"text": "relaxed terry cloth sweatpants with cargo pockets, smoke grey", "weight": 1.0},
  {"text": "cropped ripstop track jacket with mesh panels, lavender purple", "weight": 1.0},
  {"text": "oversized scuba knit pullover with thumbholes, cream ivory", "weight": 1.0},
  {"text": "high-waist nylon joggers with reflective stripes, midnight blue", "weight": 1.0},
  {"text": "fitted jersey zip-up hoodie with athletic cut, terracotta orange", "weight": 1.0},
  {"text": "longline cupro duster with side pockets, dove grey", "weight": 1.0},
  {"text": "cropped ponte track jacket with gold zippers, wine red", "weight": 1.0},
  {"text": "relaxed-fit ripstop cargo pants with utility straps, olive drab", "weight": 1.0},
  {"text": "fitted nylon bomber with quilted sleeves, slate blue", "weight": 1.0},
  {"text": "oversized terry hoodie with embroidered logo, vintage white", "weight": 1.0},
  {"text": "high-waist scuba knit shorts with side panels, plum purple", "weight": 1.0},
  {"text": "cropped jersey track set with color-block design, mint and grey", "weight": 1.0},
  {"text": "fitted ripstop anorak with half-zip closure, sunset orange", "weight": 1.0},
  {"text": "relaxed cupro joggers with wide-leg hem, steel blue", "weight": 1.0},
  {"text": "oversized nylon windbreaker with drawstring waist, neon pink", "weight": 1.0},
  {"text": "fitted ponte knit jumpsuit with belted waist, charcoal heather", "weight": 1.0},
  {"text": "cropped scuba bomber with metallic finish, rose gold", "weight": 1.0},
  {"text": "high-waist terry joggers with contrast stitching, navy blue", "weight": 1.0},
  {"text": "relaxed-fit jersey hoodie dress with kangaroo pocket, stone grey", "weight": 1.0},
  {"text": "fitted nylon track jacket with mesh inserts, emerald green", "weight": 1.0},
  {"text": "oversized ripstop coach jacket with snap buttons, sand beige", "weight": 1.0},
  {"text": "cropped cupro pullover with cowl neck, mauve pink", "weight": 1.0},
  {"text": "high-waist ponte pants with faux leather trim, black onyx", "weight": 1.0},
  {"text": "fitted scuba knit vest with zip closure, cobalt blue", "weight": 1.0},
  {"text": "longline terry cardigan with patch pockets, mushroom brown", "weight": 1.0},
  {"text": "cropped nylon track set with racing stripes, white and red", "weight": 1.0},
  {"text": "relaxed-fit jersey sweatshirt with raw hem, faded denim blue", "weight": 1.0},
  {"text": "fitted ripstop crop top with racerback design, hot pink", "weight": 1.0},
  {"text": "oversized ponte hoodie with asymmetric zip, ash grey", "weight": 1.0},
  {"text": "high-waist cupro leggings with mesh cutouts, deep purple", "weight": 1.0},
  {"text": "cropped scuba knit jacket with funnel neck, teal green", "weight": 1.0},
  {"text": "fitted nylon windbreaker with packable hood, tangerine orange", "weight": 1.0},
  {"text": "relaxed terry cloth romper with adjustable waist, soft peach", "weight": 1.0},
  {"text": "oversized ripstop parka with drawstring hem, hunter green", "weight": 1.0},
  {"text": "cropped jersey track jacket with striped cuffs, butter yellow", "weight": 1.0},
  {"text": "high-waist ponte knit skirt with side slits, burgundy wine", "weight": 1.0},
  {"text": "fitted cupro bomber with satin lining, champagne gold", "weight": 1.0},
  {"text": "longline scuba duster with belt loops, taupe brown", "weight": 1.0},
  {"text": "cropped nylon anorak with chest pocket, kelly green", "weight": 1.0},
  {"text": "relaxed-fit terry jogger set with contrast panels, cloud white", "weight": 1.0},
  {"text": "fitted ripstop track pants with ankle snaps, crimson red", "weight": 1.0},
  {"text": "oversized jersey tunic with side splits, periwinkle blue", "weight": 1.0},
  {"text": "high-waist ponte leggings with tuxedo stripe, pitch black", "weight": 1.0},
  {"text": "cropped scuba knit hoodie with cropped sleeves, apricot orange", "weight": 1.0},
  {"text": "fitted nylon track dress with sporty silhouette, ruby red", "weight": 1.0},
  {"text": "relaxed cupro wide-leg pants with elastic waist, sea foam green", "weight": 1.0},
  {"text": "oversized ripstop bomber with utility pockets, copper brown", "weight": 1.0},
  {"text": "cropped terry crop top with racerback, lilac purple", "weight": 1.0},
  {"text": "fitted jersey bodysuit with high neck, graphite grey", "weight": 1.0},
  {"text": "high-waist scuba knit joggers with tapered leg, ice blue", "weight": 1.0},
  {"text": "longline ponte cardigan with open front, caramel tan", "weight": 1.0},
  {"text": "cropped nylon puffer vest with stand collar, arctic white", "weight": 1.0},
  {"text": "relaxed-fit cupro jumpsuit with drawstring waist, olive green", "weight": 1.0},
  {"text": "fitted ripstop crop jacket with elasticized hem, magenta pink", "weight": 1.0},
  {"text": "oversized terry hoodie dress with side pockets, slate grey", "weight": 1.0},
  {"text": "high-waist jersey leggings with contour seams, mocha brown", "weight": 1.0},
  {"text": "cropped scuba bomber with perforated panels, sky blue", "weight": 1.0},
  {"text": "fitted nylon track top with quarter-zip, forest pine", "weight": 1.0},
  {"text": "relaxed ponte joggers with wide waistband, dusty mauve", "weight": 1.0},
  {"text": "oversized ripstop windbreaker with elastic cuffs, lemon yellow", "weight": 1.0},
  {"text": "cropped cupro tank with athletic cut, coral reef", "weight": 1.0},
  {"text": "fitted terry cloth shorts with side stripes, charcoal black", "weight": 1.0},
  {"text": "high-waist scuba knit capris with mesh inserts, violet purple", "weight": 1.0},
  {"text": "longline jersey cardigan with hood, cement grey", "weight": 1.0},
  {"text": "cropped nylon track jacket with holographic trim, silver metallic", "weight": 1.0},
  {"text": "relaxed-fit ponte tunic with split hem, midnight navy", "weight": 1.0},
  {"text": "fitted ripstop joggers with reflective details, neon green", "weight": 1.0},
  {"text": "oversized cupro pullover with boat neck, sand dollar", "weight": 1.0},
  {"text": "high-waist terry sweatpants with drawstring, wine burgundy", "weight": 1.0},
  {"text": "cropped scuba knit vest with zipper pockets, cerulean blue", "weight": 1.0},
  {"text": "fitted nylon windbreaker dress with sporty fit, poppy red", "weight": 1.0},
  {"text": "relaxed jersey lounge set with contrast trim, heather oatmeal", "weight": 1.0},
  {"text": "oversized ripstop anorak with snap closure, sage brush", "weight": 1.0},
  {"text": "cropped ponte blazer with notched lapels, espresso brown", "weight": 1.0},
  {"text": "high-waist cupro palazzo pants with pleats, powder blue", "weight": 1.0},
  {"text": "fitted scuba knit long-sleeve with thumbholes, rose quartz", "weight": 1.0},
  {"text": "longline terry duster with tie waist, warm grey", "weight": 1.0},
  {"text": "cropped nylon bomber with ribbed trim, seafoam green", "weight": 1.0},
  {"text": "relaxed-fit jersey hoodie with oversized hood, pebble grey", "weight": 1.0},
  {"text": "fitted ripstop crop top with built-in support, fuchsia pink", "weight": 1.0},
  {"text": "oversized ponte coat with patch pockets, camel beige", "weight": 1.0},
  {"text": "high-waist scuba knit bike shorts with side pockets, jet black", "weight": 1.0},
  {"text": "cropped cupro bomber with baseball collar, champagne beige", "weight": 1.0},
  {"text": "fitted terry joggers with elastic ankles, storm blue", "weight": 1.0},
  {"text": "relaxed nylon track pants with side buttons, ivory cream", "weight": 1.0},
  {"text": "oversized jersey poncho with asymmetric hem, charcoal heather", "weight": 1.0},
  {"text": "cropped ripstop windbreaker with cinched waist, tangerine", "weight": 1.0},
  {"text": "high-waist ponte pencil skirt with athletic stretch, deep plum", "weight": 1.0},
  {"text": "fitted scuba knit jacket with moto styling, gunmetal grey", "weight": 1.0},
  {"text": "longline cupro vest with side slits, almond tan", "weight": 1.0},
  {"text": "cropped nylon track top with mesh shoulders, electric purple", "weight": 1.0},
  {"text": "relaxed-fit terry romper with v-neck, blush pink", "weight": 1.0},
  {"text": "fitted jersey crop hoodie with drawstring, olive green", "weight": 1.0},
  {"text": "oversized ripstop jacket with toggle closure, burnt orange", "weight": 1.0},
  {"text": "high-waist ponte joggers with faux fly, carbon black", "weight": 1.0},
  {"text": "cropped scuba knit pullover with crew neck, peacock blue", "weight": 1.0},
  {"text": "fitted nylon windbreaker with color-block design, grey and pink", "weight": 1.0},
  {"text": "relaxed cupro wide-leg jumpsuit with halter neck, terracotta", "weight": 1.0},
  {"text": "oversized terry hoodie with embroidered patch, cream white", "weight": 1.0},
  {"text": "cropped jersey tank with racerback straps, sunshine yellow", "weight": 1.0},
  {"text": "high-waist ripstop cargo joggers with buckle details, khaki green", "weight": 1.0},
  {"text": "fitted ponte bodycon dress with sporty seams, wine red", "weight": 1.0},
  {"text": "longline scuba knit cardigan with open drape, misty grey", "weight": 1.0},
  {"text": "cropped nylon puffer jacket with quilted panels, cobalt blue", "weight": 1.0},
  {"text": "relaxed-fit cupro lounge pants with wide leg, stone beige", "weight": 1.0},
  {"text": "fitted terry cloth crop top with cap sleeves, coral pink", "weight": 1.0},
  {"text": "oversized jersey tunic dress with hoodie, charcoal grey", "weight": 1.0},
  {"text": "high-waist scuba knit leggings with color-block panels, navy and white", "weight": 1.0},
  {"text": "cropped ripstop vest with mesh back, lime green", "weight": 1.0},
  {"text": "fitted nylon track jacket with princess seams, berry purple", "weight": 1.0},
  {"text": "relaxed ponte jogger set with cropped top, mushroom taupe", "weight": 1.0},
  {"text": "oversized cupro kimono with tie closure, sage green", "weight": 1.0},
  {"text": "cropped scuba bomber with zipper sleeves, rose gold", "weight": 1.0},
  {"text": "high-waist jersey shorts with compression fit, midnight black", "weight": 1.0},
  {"text": "fitted ripstop anorak with athletic cut, sunset pink", "weight": 1.0},
  {"text": "longline terry cardigan with shawl collar, oatmeal cream", "weight": 1.0},
  {"text": "cropped nylon windbreaker with retro stripes, red and white", "weight": 1.0},
  {"text": "relaxed-fit ponte tunic with side vents, steel blue", "weight": 1.0},
  {"text": "fitted cupro bodysuit with scoop neck, bronze brown", "weight": 1.0},
  {"text": "oversized scuba knit hoodie with kangaroo pocket, lavender grey", "weight": 1.0},
  {"text": "high-waist terry joggers with cuffed ankles, emerald green", "weight": 1.0},
  {"text": "cropped jersey zip-up with athletic stripes, peach sorbet", "weight": 1.0},
  {"text": "fitted ripstop crop jacket with stand collar, electric blue", "weight": 1.0},
  {"text": "relaxed nylon track set with matching jacket, ash grey", "weight": 1.0},
  {"text": "oversized ponte coat with belt, chocolate brown", "weight": 1.0},
  {"text": "cropped scuba knit tank with high neck, aqua blue", "weight": 1.0},
  {"text": "high-waist cupro culottes with pleated front, sand beige", "weight": 1.0},
  {"text": "fitted terry cloth leggings with side mesh, charcoal black", "weight": 1.0},
  {"text": "longline jersey cardigan with pockets, dove grey", "weight": 1.0},
  {"text": "cropped nylon bomber with iridescent finish, pearl white", "weight": 1.0},
  {"text": "relaxed-fit ripstop joggers with cargo pockets, army green", "weight": 1.0},
  {"text": "fitted ponte blazer with zip pockets, deep navy", "weight": 1.0},
  {"text": "oversized cupro pullover with funnel neck, dusty rose", "weight": 1.0},
  {"text": "high-waist scuba knit flared pants with seams, burgundy wine", "weight": 1.0},
  {"text": "cropped terry hoodie with cropped sleeves, soft pink", "weight": 1.0},
  {"text": "fitted nylon track dress with racerback, crimson red", "weight": 1.0},
  {"text": "relaxed jersey lounge jumpsuit with drawstring, heather grey", "weight": 1.0},
  {"text": "oversized ripstop windbreaker with logo tape, neon yellow", "weight": 1.0},
  {"text": "cropped scuba knit jacket with asymmetric zip, slate blue", "weight": 1.0},
  {"text": "high-waist ponte leggings with faux leather panels, pitch black", "weight": 1.0},
  {"text": "fitted cupro crop top with square neck, caramel tan", "weight": 1.0},
  {"text": "longline terry duster with side pockets, warm taupe", "weight": 1.0},
  {"text": "cropped nylon windbreaker with hood, kelly green", "weight": 1.0},
  {"text": "relaxed-fit jersey sweatpants with side stripes, cloud grey", "weight": 1.0},
  {"text": "fitted ripstop shorts with compression liner, hot pink", "weight": 1.0},
  {"text": "oversized ponte hoodie with drop shoulders, cement grey", "weight": 1.0},
  {"text": "high-waist scuba knit joggers with contour seams, teal blue", "weight": 1.0},
  {"text": "cropped cupro bomber with ribbed waist, champagne gold", "weight": 1.0},
  {"text": "fitted terry cloth romper with belted waist, peach cream", "weight": 1.0},
  {"text": "relaxed nylon track jacket with color panels, navy and yellow", "weight": 1.0},
  {"text": "oversized jersey tunic with v-neck, periwinkle blue", "weight": 1.0},
  {"text": "cropped ripstop vest with snap buttons, copper orange", "weight": 1.0},
  {"text": "high-waist ponte shorts with side pockets, charcoal heather", "weight": 1.0},
  {"text": "fitted scuba knit long-sleeve with crew neck, ruby red", "weight": 1.0},
  {"text": "longline cupro cardigan with waterfall front, sand grey", "weight": 1.0},
  {"text": "cropped nylon track top with mesh inserts, violet purple", "weight": 1.0},
  {"text": "relaxed-fit terry jogger set with crop top, stone white", "weight": 1.0},
  {"text": "fitted jersey bodysuit with long sleeves, forest green", "weight": 1.0},
  {"text": "oversized ripstop parka with faux fur trim, ice blue", "weight": 1.0},
  {"text": "high-waist ponte pencil pants with seam detail, espresso brown", "weight": 1.0},
  {"text": "cropped scuba bomber with perforated sides, sky blue", "weight": 1.0},
  {"text": "fitted cupro tank with scooped back, apricot orange", "weight": 1.0},
  {"text": "relaxed nylon windbreaker set with joggers, smoke grey", "weight": 1.0},
  {"text": "oversized terry hoodie dress with pockets, dusty mauve", "weight": 1.0},
  {"text": "cropped jersey zip-up with thumbholes, lemon yellow", "weight": 1.0},
  {"text": "high-waist ripstop leggings with reflective trim, jet black", "weight": 1.0},
  {"text": "fitted ponte knit jumpsuit with zipper front, midnight navy", "weight": 1.0},
  {"text": "longline scuba knit vest with drape, warm grey", "weight": 1.0},
  {"text": "cropped nylon bomber with quilted lining, rose pink", "weight": 1.0},
  {"text": "relaxed-fit cupro wide-leg set with crop top, sage green", "weight": 1.0},
  {"text": "fitted terry cloth crop hoodie with strings, coral reef", "weight": 1.0},
  {"text": "oversized jersey poncho with hood, pebble grey", "weight": 1.0},
  {"text": "high-waist scuba knit capris with mesh panels, magenta pink", "weight": 1.0},
  {"text": "cropped ripstop anorak with half-zip, seafoam green", "weight": 1.0},
  {"text": "fitted nylon track pants with ankle zips, cobalt blue", "weight": 1.0},
  {"text": "relaxed ponte tunic dress with belt loops, camel tan", "weight": 1.0},
  {"text": "oversized cupro pullover with dolman sleeves, powder blue", "weight": 1.0},
  {"text": "cropped scuba knit hoodie with cropped fit, lilac purple", "weight": 1.0},
  {"text": "high-waist terry sweatpants with contrast panels, graphite grey", "weight": 1.0},
  {"text": "fitted jersey crop top with long sleeves, terracotta orange", "weight": 1.0},
  {"text": "longline ripstop duster with drawstring, olive drab", "weight": 1.0},
  {"text": "cropped nylon windbreaker with elastic hem, neon pink", "weight": 1.0},
  {"text": "relaxed-fit ponte joggers with wide waist, wine burgundy", "weight": 1.0},
  {"text": "fitted cupro bodysuit with racerback, mocha brown", "weight": 1.0},
  {"text": "oversized scuba knit cardigan with pockets, cement grey", "weight": 1.0},
  {"text": "high-waist ripstop cargo shorts with buckles, khaki tan", "weight": 1.0},
  {"text": "cropped terry cloth tank with athletic cut, poppy red", "weight": 1.0},
  {"text": "fitted nylon track jacket with contour seams, emerald green", "weight": 1.0},
  {"text": "relaxed jersey lounge set with hoodie, heather oatmeal", "weight": 1.0},
  {"text": "oversized ponte coat with notched collar, espresso brown", "weight": 1.0},
  {"text": "cropped scuba bomber with metallic zippers, silver grey", "weight": 1.0},
  {"text": "high-waist cupro palazzo joggers with pleats, blush pink", "weight": 1.0},
  {"text": "fitted ripstop crop jacket with mesh lining, electric purple", "weight": 1.0},
  {"text": "longline terry cardigan with tie belt, warm taupe", "weight": 1.0},
  {"text": "cropped nylon track set with striped trim, white and navy", "weight": 1.0},
  {"text": "relaxed-fit jersey tunic with side slits, storm blue", "weight": 1.0},
  {"text": "fitted ponte leggings with tuxedo stripe, carbon black", "weight": 1.0},
  {"text": "oversized cupro kimono jacket with belt, champagne beige", "weight": 1.0},
  {"text": "high-waist scuba knit shorts with compression fit, deep plum", "weight": 1.0},
  {"text": "cropped terry hoodie with kangaroo pocket, ivory cream", "weight": 1.0},
  {"text": "fitted nylon windbreaker dress with sporty cut, fuchsia pink", "weight": 1.0},
  {"text": "relaxed ripstop joggers with elastic cuffs, burnt orange", "weight": 1.0},
  {"text": "oversized jersey cardigan with open front, charcoal heather", "weight": 1.0},
  {"text": "cropped scuba knit vest with high neck, peacock blue", "weight": 1.0},
  {"text": "high-waist ponte pants with wide leg, gunmetal grey", "weight": 1.0},
  {"text": "fitted cupro crop top with halter neck, sunset pink", "weight": 1.0},
  {"text": "longline nylon duster with snap closure, almond tan", "weight": 1.0},
  {"text": "cropped jersey zip-up with racing stripes, red and black", "weight": 1.0},
  {"text": "relaxed-fit terry jogger romper with pockets, soft peach", "weight": 1.0},
  {"text": "fitted ripstop track pants with reflective logos, lime green", "weight": 1.0},
  {"text": "oversized ponte hoodie dress with drawstring, misty grey", "weight": 1.0},
  {"text": "high-waist scuba knit leggings with side cutouts, wine red", "weight": 1.0},
  {"text": "cropped cupro bomber with satin sleeves, bronze brown", "weight": 1.0},
  {"text": "fitted nylon track top with quarter-zip, berry purple", "weight": 1.0},
  {"text": "relaxed jersey lounge pants with wide leg, lavender grey", "weight": 1.0},
  {"text": "oversized ripstop windbreaker with toggle hem, aqua blue", "weight": 1.0},
  {"text": "cropped scuba knit jacket with funnel collar, rose gold", "weight": 1.0},
  {"text": "high-waist terry shorts with side stripes, midnight black", "weight": 1.0},
  {"text": "fitted ponte blazer with athletic cut, deep navy", "weight": 1.0},
  {"text": "longline cupro vest with open drape, sand beige", "weight": 1.0},
  {"text": "cropped nylon bomber with holographic panels, pearl white", "weight": 1.0},
  {"text": "relaxed-fit jersey hoodie with oversized fit, dove grey", "weight": 1.0},
  {"text": "fitted ripstop crop top with built-in layer, tangerine orange", "weight": 1.0},
  {"text": "oversized scuba knit pullover with boat neck, dusty rose", "weight": 1.0},
  {"text": "high-waist ponte joggers with faux pockets, charcoal black", "weight": 1.0},
  {"text": "cropped terry cloth crop hoodie with strings, coral pink", "weight": 1.0},
  {"text": "fitted nylon windbreaker with color-block, grey and teal", "weight": 1.0},
  {"text": "relaxed cupro wide-leg jumpsuit with v-neck, terracotta", "weight": 1.0},
  {"text": "oversized jersey tunic dress with pockets, heather grey", "weight": 1.0},
  {"text": "cropped ripstop vest with mesh inserts, neon yellow", "weight": 1.0},
  {"text": "high-waist scuba knit bike shorts with panels, slate blue", "weight": 1.0},
  {"text": "fitted ponte bodycon dress with athletic seams, burgundy wine", "weight": 1.0}
]
